{
  "fetched_at": "2026-05-19T04:10:25.920011+00:00",
  "movies": [
    {
      "title": "Karuppu",
      "movie_info": {
        "title": "Karuppu",
        "poster_url": "https://imgix.hoyts.co.nz/mx/posters/nz/karuppu-7171fb8c.jpg",
        "release_date": "2026-05-15",
        "running_time_mins": 152,
        "director": "RJ  Balaji",
        "rating": "R13",
        "ec_ids": [
          "HO00018304"
        ],
        "hoyts_ids": [
          "HO00008409"
        ]
      },
      "overall_stats": {
        "sessions": 20,
        "total_seats": 1914,
        "sold_seats": 370,
        "available_seats": 1442,
        "occupancy_pct": 19.3,
        "revenue": 9277.0,
        "dates_count": 9,
        "hoyts_sessions": 13,
        "ec_sessions": 7,
        "hoyts_revenue": 3391.0,
        "ec_revenue": 5886.0
      },
      "dates": [
        {
          "date": "2026-05-19",
          "overall_stats": {
            "sessions": 6,
            "total_seats": 686,
            "sold_seats": 315,
            "available_seats": 335,
            "occupancy_pct": 45.9,
            "revenue": 7881.5
          },
          "platforms": {
            "hoyts": {
              "overall_stats": {
                "sessions": 3,
                "total_seats": 354,
                "sold_seats": 99,
                "available_seats": 225,
                "occupancy_pct": 28.0,
                "revenue": 2371.0
              },
              "locations": {
                "1001": {
                  "cinema_name": "1001",
                  "overall_stats": {
                    "sessions": 1,
                    "total_seats": 123,
                    "sold_seats": 30,
                    "available_seats": 79,
                    "occupancy_pct": 24.4,
                    "revenue": 780.0
                  },
                  "sessions": [
                    {
                      "session_id": 373205,
                      "start_time": "2026-05-19T21:15:00",
                      "stats": {
                        "total_seats": 123,
                        "sold_seats": 30,
                        "unavailable": 14,
                        "available_seats": 79,
                        "occupancy_pct": 27.5,
                        "revenue": 780.0
                      },
                      "screen": "Cinema 3"
                    }
                  ]
                },
                "1005": {
                  "cinema_name": "1005",
                  "overall_stats": {
                    "sessions": 1,
                    "total_seats": 154,
                    "sold_seats": 14,
                    "available_seats": 132,
                    "occupancy_pct": 9.1,
                    "revenue": 161.0
                  },
                  "sessions": [
                    {
                      "session_id": 326256,
                      "start_time": "2026-05-19T20:45:00",
                      "stats": {
                        "total_seats": 154,
                        "sold_seats": 14,
                        "unavailable": 8,
                        "available_seats": 132,
                        "occupancy_pct": 9.6,
                        "revenue": 161.0
                      },
                      "screen": "Cinema 4"
                    }
                  ]
                },
                "ORMCIN": {
                  "cinema_name": "ORMCIN",
                  "overall_stats": {
                    "sessions": 1,
                    "total_seats": 77,
                    "sold_seats": 55,
                    "available_seats": 14,
                    "occupancy_pct": 71.4,
                    "revenue": 1430.0
                  },
                  "sessions": [
                    {
                      "session_id": 80820,
                      "start_time": "2026-05-19T21:00:00",
                      "stats": {
                        "total_seats": 77,
                        "sold_seats": 55,
                        "unavailable": 8,
                        "available_seats": 14,
                        "occupancy_pct": 79.7,
                        "revenue": 1430.0
                      },
                      "screen": "Cinema 02"
                    }
                  ]
                }
              }
            },
            "event_cinemas": {
              "overall_stats": {
                "sessions": 3,
                "total_seats": 332,
                "sold_seats": 216,
                "available_seats": 110,
                "occupancy_pct": 65.1,
                "revenue": 5510.5
              },
              "locations": {
                "502": {
                  "cinema_name": "Queen Street (Auckland)",
                  "overall_stats": {
                    "sessions": 1,
                    "total_seats": 77,
                    "sold_seats": 56,
                    "available_seats": 19,
                    "occupancy_pct": 72.7,
                    "revenue": 1540.0
                  },
                  "sessions": [
                    {
                      "session_id": 2359078,
                      "start_time": "2026-05-19T20:15",
                      "stats": {
                        "total_seats": 77,
                        "available_seats": 19,
                        "sold_seats": 56,
                        "wheelchair_seats": 2,
                        "occupancy_pct": 72.7,
                        "revenue": 1540.0
                      },
                      "screen_type": "Std",
                      "screen_name": "11",
                      "ho_code": "HO00018304",
                      "adult_price": 27.5
                    }
                  ]
                },
                "505": {
                  "cinema_name": "Westgate (Auckland)",
                  "overall_stats": {
                    "sessions": 1,
                    "total_seats": 105,
                    "sold_seats": 77,
                    "available_seats": 26,
                    "occupancy_pct": 73.3,
                    "revenue": 1771.0
                  },
                  "sessions": [
                    {
                      "session_id": 2359086,
                      "start_time": "2026-05-19T19:40",
                      "stats": {
                        "total_seats": 105,
                        "available_seats": 26,
                        "sold_seats": 77,
                        "wheelchair_seats": 2,
                        "occupancy_pct": 73.3,
                        "revenue": 1771.0
                      },
                      "screen_type": "Std",
                      "screen_name": "2",
                      "ho_code": "HO00018304",
                      "adult_price": 23.0
                    }
                  ]
                },
                "511": {
                  "cinema_name": "Queensgate (Wellington)",
                  "overall_stats": {
                    "sessions": 1,
                    "total_seats": 150,
                    "sold_seats": 83,
                    "available_seats": 65,
                    "occupancy_pct": 55.3,
                    "revenue": 2199.5
                  },
                  "sessions": [
                    {
                      "session_id": 2359071,
                      "start_time": "2026-05-19T20:45",
                      "stats": {
                        "total_seats": 150,
                        "available_seats": 65,
                        "sold_seats": 83,
                        "wheelchair_seats": 2,
                        "occupancy_pct": 55.3,
                        "revenue": 2199.5
                      },
                      "screen_type": "Std",
                      "screen_name": "3",
                      "ho_code": "HO00018304",
                      "adult_price": 26.5
                    }
                  ]
                }
              }
            }
          }
        },
        {
          "date": "2026-05-20",
          "overall_stats": {
            "sessions": 7,
            "total_seats": 731,
            "sold_seats": 29,
            "available_seats": 664,
            "occupancy_pct": 4.0,
            "revenue": 719.5
          },
          "platforms": {
            "hoyts": {
              "overall_stats": {
                "sessions": 3,
                "total_seats": 354,
                "sold_seats": 15,
                "available_seats": 309,
                "occupancy_pct": 4.2,
                "revenue": 344.0
              },
              "locations": {
                "1001": {
                  "cinema_name": "1001",
                  "overall_stats": {
                    "sessions": 1,
                    "total_seats": 123,
                    "sold_seats": 0,
                    "available_seats": 109,
                    "occupancy_pct": 0.0,
                    "revenue": 0.0
                  },
                  "sessions": [
                    {
                      "session_id": 373245,
                      "start_time": "2026-05-20T21:15:00",
                      "stats": {
                        "total_seats": 123,
                        "sold_seats": 0,
                        "unavailable": 14,
                        "available_seats": 109,
                        "occupancy_pct": 0.0,
                        "revenue": 0.0
                      },
                      "screen": "Cinema 3"
                    }
                  ]
                },
                "1005": {
                  "cinema_name": "1005",
                  "overall_stats": {
                    "sessions": 1,
                    "total_seats": 154,
                    "sold_seats": 4,
                    "available_seats": 142,
                    "occupancy_pct": 2.6,
                    "revenue": 58.0
                  },
                  "sessions": [
                    {
                      "session_id": 326290,
                      "start_time": "2026-05-20T20:45:00",
                      "stats": {
                        "total_seats": 154,
                        "sold_seats": 4,
                        "unavailable": 8,
                        "available_seats": 142,
                        "occupancy_pct": 2.7,
                        "revenue": 58.0
                      },
                      "screen": "Cinema 4"
                    }
                  ]
                },
                "ORMCIN": {
                  "cinema_name": "ORMCIN",
                  "overall_stats": {
                    "sessions": 1,
                    "total_seats": 77,
                    "sold_seats": 11,
                    "available_seats": 58,
                    "occupancy_pct": 14.3,
                    "revenue": 286.0
                  },
                  "sessions": [
                    {
                      "session_id": 80859,
                      "start_time": "2026-05-20T21:00:00",
                      "stats": {
                        "total_seats": 77,
                        "sold_seats": 11,
                        "unavailable": 8,
                        "available_seats": 58,
                        "occupancy_pct": 15.9,
                        "revenue": 286.0
                      },
                      "screen": "Cinema 02"
                    }
                  ]
                }
              }
            },
            "event_cinemas": {
              "overall_stats": {
                "sessions": 4,
                "total_seats": 377,
                "sold_seats": 14,
                "available_seats": 355,
                "occupancy_pct": 3.7,
                "revenue": 375.5
              },
              "locations": {
                "502": {
                  "cinema_name": "Queen Street (Auckland)",
                  "overall_stats": {
                    "sessions": 1,
                    "total_seats": 50,
                    "sold_seats": 1,
                    "available_seats": 47,
                    "occupancy_pct": 2.0,
                    "revenue": 67.0
                  },
                  "sessions": [
                    {
                      "session_id": 2359077,
                      "start_time": "2026-05-20T20:30",
                      "stats": {
                        "total_seats": 50,
                        "available_seats": 47,
                        "sold_seats": 1,
                        "wheelchair_seats": 2,
                        "occupancy_pct": 2.0,
                        "revenue": 67.0
                      },
                      "screen_type": "Std",
                      "screen_name": "5",
                      "ho_code": "HO00018304",
                      "adult_price": 67.0
                    }
                  ]
                },
                "505": {
                  "cinema_name": "Westgate (Auckland)",
                  "overall_stats": {
                    "sessions": 1,
                    "total_seats": 115,
                    "sold_seats": 6,
                    "available_seats": 107,
                    "occupancy_pct": 5.2,
                    "revenue": 138.0
                  },
                  "sessions": [
                    {
                      "session_id": 2359087,
                      "start_time": "2026-05-20T20:45",
                      "stats": {
                        "total_seats": 115,
                        "available_seats": 107,
                        "sold_seats": 6,
                        "wheelchair_seats": 2,
                        "occupancy_pct": 5.2,
                        "revenue": 138.0
                      },
                      "screen_type": "Std",
                      "screen_name": "1",
                      "ho_code": "HO00018304",
                      "adult_price": 23.0
                    }
                  ]
                },
                "511": {
                  "cinema_name": "Queensgate (Wellington)",
                  "overall_stats": {
                    "sessions": 1,
                    "total_seats": 150,
                    "sold_seats": 2,
                    "available_seats": 146,
                    "occupancy_pct": 1.3,
                    "revenue": 53.0
                  },
                  "sessions": [
                    {
                      "session_id": 2359072,
                      "start_time": "2026-05-20T20:45",
                      "stats": {
                        "total_seats": 150,
                        "available_seats": 146,
                        "sold_seats": 2,
                        "wheelchair_seats": 2,
                        "occupancy_pct": 1.3,
                        "revenue": 53.0
                      },
                      "screen_type": "Std",
                      "screen_name": "3",
                      "ho_code": "HO00018304",
                      "adult_price": 26.5
                    }
                  ]
                },
                "518": {
                  "cinema_name": "Blenheim",
                  "overall_stats": {
                    "sessions": 1,
                    "total_seats": 62,
                    "sold_seats": 5,
                    "available_seats": 55,
                    "occupancy_pct": 8.1,
                    "revenue": 117.5
                  },
                  "sessions": [
                    {
                      "session_id": 2359083,
                      "start_time": "2026-05-20T20:45",
                      "stats": {
                        "total_seats": 62,
                        "available_seats": 55,
                        "sold_seats": 5,
                        "wheelchair_seats": 2,
                        "occupancy_pct": 8.1,
                        "revenue": 117.5
                      },
                      "screen_type": "Std",
                      "screen_name": "2",
                      "ho_code": "HO00018304",
                      "adult_price": 23.5
                    }
                  ]
                }
              }
            }
          }
        },
        {
          "date": "2026-05-21",
          "overall_stats": {
            "sessions": 1,
            "total_seats": 71,
            "sold_seats": 2,
            "available_seats": 65,
            "occupancy_pct": 2.8,
            "revenue": 52.0
          },
          "platforms": {
            "hoyts": {
              "overall_stats": {
                "sessions": 1,
                "total_seats": 71,
                "sold_seats": 2,
                "available_seats": 65,
                "occupancy_pct": 2.8,
                "revenue": 52.0
              },
              "locations": {
                "ORMCIN": {
                  "cinema_name": "ORMCIN",
                  "overall_stats": {
                    "sessions": 1,
                    "total_seats": 71,
                    "sold_seats": 2,
                    "available_seats": 65,
                    "occupancy_pct": 2.8,
                    "revenue": 52.0
                  },
                  "sessions": [
                    {
                      "session_id": 81008,
                      "start_time": "2026-05-21T20:15:00",
                      "stats": {
                        "total_seats": 71,
                        "sold_seats": 2,
                        "unavailable": 4,
                        "available_seats": 65,
                        "occupancy_pct": 3.0,
                        "revenue": 52.0
                      },
                      "screen": "Cinema 05"
                    }
                  ]
                }
              }
            },
            "event_cinemas": {
              "overall_stats": {
                "sessions": 0,
                "total_seats": 0,
                "sold_seats": 0,
                "available_seats": 0,
                "occupancy_pct": 0.0,
                "revenue": 0
              },
              "locations": {}
            }
          }
        },
        {
          "date": "2026-05-22",
          "overall_stats": {
            "sessions": 1,
            "total_seats": 71,
            "sold_seats": 21,
            "available_seats": 46,
            "occupancy_pct": 29.6,
            "revenue": 546.0
          },
          "platforms": {
            "hoyts": {
              "overall_stats": {
                "sessions": 1,
                "total_seats": 71,
                "sold_seats": 21,
                "available_seats": 46,
                "occupancy_pct": 29.6,
                "revenue": 546.0
              },
              "locations": {
                "ORMCIN": {
                  "cinema_name": "ORMCIN",
                  "overall_stats": {
                    "sessions": 1,
                    "total_seats": 71,
                    "sold_seats": 21,
                    "available_seats": 46,
                    "occupancy_pct": 29.6,
                    "revenue": 546.0
                  },
                  "sessions": [
                    {
                      "session_id": 81039,
                      "start_time": "2026-05-22T20:30:00",
                      "stats": {
                        "total_seats": 71,
                        "sold_seats": 21,
                        "unavailable": 4,
                        "available_seats": 46,
                        "occupancy_pct": 31.3,
                        "revenue": 546.0
                      },
                      "screen": "Cinema 05"
                    }
                  ]
                }
              }
            },
            "event_cinemas": {
              "overall_stats": {
                "sessions": 0,
                "total_seats": 0,
                "sold_seats": 0,
                "available_seats": 0,
                "occupancy_pct": 0.0,
                "revenue": 0
              },
              "locations": {}
            }
          }
        },
        {
          "date": "2026-05-23",
          "overall_stats": {
            "sessions": 1,
            "total_seats": 71,
            "sold_seats": 0,
            "available_seats": 67,
            "occupancy_pct": 0.0,
            "revenue": 0.0
          },
          "platforms": {
            "hoyts": {
              "overall_stats": {
                "sessions": 1,
                "total_seats": 71,
                "sold_seats": 0,
                "available_seats": 67,
                "occupancy_pct": 0.0,
                "revenue": 0.0
              },
              "locations": {
                "ORMCIN": {
                  "cinema_name": "ORMCIN",
                  "overall_stats": {
                    "sessions": 1,
                    "total_seats": 71,
                    "sold_seats": 0,
                    "available_seats": 67,
                    "occupancy_pct": 0.0,
                    "revenue": 0.0
                  },
                  "sessions": [
                    {
                      "session_id": 81062,
                      "start_time": "2026-05-23T20:15:00",
                      "stats": {
                        "total_seats": 71,
                        "sold_seats": 0,
                        "unavailable": 4,
                        "available_seats": 67,
                        "occupancy_pct": 0.0,
                        "revenue": 0.0
                      },
                      "screen": "Cinema 05"
                    }
                  ]
                }
              }
            },
            "event_cinemas": {
              "overall_stats": {
                "sessions": 0,
                "total_seats": 0,
                "sold_seats": 0,
                "available_seats": 0,
                "occupancy_pct": 0.0,
                "revenue": 0
              },
              "locations": {}
            }
          }
        },
        {
          "date": "2026-05-24",
          "overall_stats": {
            "sessions": 1,
            "total_seats": 71,
            "sold_seats": 0,
            "available_seats": 67,
            "occupancy_pct": 0.0,
            "revenue": 0.0
          },
          "platforms": {
            "hoyts": {
              "overall_stats": {
                "sessions": 1,
                "total_seats": 71,
                "sold_seats": 0,
                "available_seats": 67,
                "occupancy_pct": 0.0,
                "revenue": 0.0
              },
              "locations": {
                "ORMCIN": {
                  "cinema_name": "ORMCIN",
                  "overall_stats": {
                    "sessions": 1,
                    "total_seats": 71,
                    "sold_seats": 0,
                    "available_seats": 67,
                    "occupancy_pct": 0.0,
                    "revenue": 0.0
                  },
                  "sessions": [
                    {
                      "session_id": 81198,
                      "start_time": "2026-05-24T20:15:00",
                      "stats": {
                        "total_seats": 71,
                        "sold_seats": 0,
                        "unavailable": 4,
                        "available_seats": 67,
                        "occupancy_pct": 0.0,
                        "revenue": 0.0
                      },
                      "screen": "Cinema 05"
                    }
                  ]
                }
              }
            },
            "event_cinemas": {
              "overall_stats": {
                "sessions": 0,
                "total_seats": 0,
                "sold_seats": 0,
                "available_seats": 0,
                "occupancy_pct": 0.0,
                "revenue": 0
              },
              "locations": {}
            }
          }
        },
        {
          "date": "2026-05-25",
          "overall_stats": {
            "sessions": 1,
            "total_seats": 71,
            "sold_seats": 0,
            "available_seats": 67,
            "occupancy_pct": 0.0,
            "revenue": 0.0
          },
          "platforms": {
            "hoyts": {
              "overall_stats": {
                "sessions": 1,
                "total_seats": 71,
                "sold_seats": 0,
                "available_seats": 67,
                "occupancy_pct": 0.0,
                "revenue": 0.0
              },
              "locations": {
                "ORMCIN": {
                  "cinema_name": "ORMCIN",
                  "overall_stats": {
                    "sessions": 1,
                    "total_seats": 71,
                    "sold_seats": 0,
                    "available_seats": 67,
                    "occupancy_pct": 0.0,
                    "revenue": 0.0
                  },
                  "sessions": [
                    {
                      "session_id": 81108,
                      "start_time": "2026-05-25T20:15:00",
                      "stats": {
                        "total_seats": 71,
                        "sold_seats": 0,
                        "unavailable": 4,
                        "available_seats": 67,
                        "occupancy_pct": 0.0,
                        "revenue": 0.0
                      },
                      "screen": "Cinema 05"
                    }
                  ]
                }
              }
            },
            "event_cinemas": {
              "overall_stats": {
                "sessions": 0,
                "total_seats": 0,
                "sold_seats": 0,
                "available_seats": 0,
                "occupancy_pct": 0.0,
                "revenue": 0
              },
              "locations": {}
            }
          }
        },
        {
          "date": "2026-05-26",
          "overall_stats": {
            "sessions": 1,
            "total_seats": 71,
            "sold_seats": 3,
            "available_seats": 64,
            "occupancy_pct": 4.2,
            "revenue": 78.0
          },
          "platforms": {
            "hoyts": {
              "overall_stats": {
                "sessions": 1,
                "total_seats": 71,
                "sold_seats": 3,
                "available_seats": 64,
                "occupancy_pct": 4.2,
                "revenue": 78.0
              },
              "locations": {
                "ORMCIN": {
                  "cinema_name": "ORMCIN",
                  "overall_stats": {
                    "sessions": 1,
                    "total_seats": 71,
                    "sold_seats": 3,
                    "available_seats": 64,
                    "occupancy_pct": 4.2,
                    "revenue": 78.0
                  },
                  "sessions": [
                    {
                      "session_id": 81131,
                      "start_time": "2026-05-26T20:15:00",
                      "stats": {
                        "total_seats": 71,
                        "sold_seats": 3,
                        "unavailable": 4,
                        "available_seats": 64,
                        "occupancy_pct": 4.5,
                        "revenue": 78.0
                      },
                      "screen": "Cinema 05"
                    }
                  ]
                }
              }
            },
            "event_cinemas": {
              "overall_stats": {
                "sessions": 0,
                "total_seats": 0,
                "sold_seats": 0,
                "available_seats": 0,
                "occupancy_pct": 0.0,
                "revenue": 0
              },
              "locations": {}
            }
          }
        },
        {
          "date": "2026-05-27",
          "overall_stats": {
            "sessions": 1,
            "total_seats": 71,
            "sold_seats": 0,
            "available_seats": 67,
            "occupancy_pct": 0.0,
            "revenue": 0.0
          },
          "platforms": {
            "hoyts": {
              "overall_stats": {
                "sessions": 1,
                "total_seats": 71,
                "sold_seats": 0,
                "available_seats": 67,
                "occupancy_pct": 0.0,
                "revenue": 0.0
              },
              "locations": {
                "ORMCIN": {
                  "cinema_name": "ORMCIN",
                  "overall_stats": {
                    "sessions": 1,
                    "total_seats": 71,
                    "sold_seats": 0,
                    "available_seats": 67,
                    "occupancy_pct": 0.0,
                    "revenue": 0.0
                  },
                  "sessions": [
                    {
                      "session_id": 81154,
                      "start_time": "2026-05-27T20:15:00",
                      "stats": {
                        "total_seats": 71,
                        "sold_seats": 0,
                        "unavailable": 4,
                        "available_seats": 67,
                        "occupancy_pct": 0.0,
                        "revenue": 0.0
                      },
                      "screen": "Cinema 05"
                    }
                  ]
                }
              }
            },
            "event_cinemas": {
              "overall_stats": {
                "sessions": 0,
                "total_seats": 0,
                "sold_seats": 0,
                "available_seats": 0,
                "occupancy_pct": 0.0,
                "revenue": 0
              },
              "locations": {}
            }
          }
        }
      ]
    }
  ]
}